autoverse_cli-0.28.2.dist-info/licenses/LICENSE
avrs/__init__.py
avrs/app_version.py
avrs/argparse_help.py
avrs/avrs.py
avrs/can_tool.py
avrs/can_tool_util.py
avrs/cfg.py
avrs/launcher.py
avrs/launcher_util.py
avrs/race_cloud.py
avrs/race_cloud_bridge_can.py
avrs/race_cloud_cfg_util.py
avrs/race_cloud_fwd_api.py
avrs/race_cloud_util.py
avrs/shell_completion.py
avrs/simconfig.py
avrs/simconfig_util.py
avrs/tests.py
avrs/util.py
avrs/requests/change_camera.py
avrs/requests/code_booz.py
avrs/requests/demo.py
avrs/requests/dump_sim_config.py
avrs/requests/environment.py
avrs/requests/fault_injection.py
avrs/requests/get_object_config.py
avrs/requests/get_web_viz_meta.py
avrs/requests/leaderboard.py
avrs/requests/list_sim_objects.py
avrs/requests/log_path.py
avrs/requests/misc.py
avrs/requests/move_to_landmark.py
avrs/requests/npc.py
avrs/requests/race_control.py
avrs/requests/request.py
avrs/requests/reset_to_track.py
avrs/requests/rest_request.py
avrs/requests/restart.py
avrs/requests/scenario_control.py
avrs/requests/spawn_object.py
avrs/requests/teleport.py
avrs/requests/toggle_hud.py
avrs/requests/vd.py
avrs/requests/vehicle_input.py
avrs/requests/vehicle_replay.py
autoverse_cli-0.28.2.dist-info/METADATA
autoverse_cli-0.28.2.dist-info/WHEEL
autoverse_cli-0.28.2.dist-info/entry_points.txt
autoverse_cli-0.28.2.dist-info/top_level.txt
autoverse_cli-0.28.2.dist-info/RECORD
