Metadata-Version: 2.4
Name: autoverse-cli
Version: 0.28.2
Summary: The Autoverse CLI
Author-email: Dan Kamrath <dan.kamrath@autonomalabs.com>
License: # End-User License Agreement (EULA) of the Autonoma AutoVerse CLI
Classifier: Programming Language :: Python :: 3
Classifier: Operating System :: OS Independent
Requires-Python: >=3.8
License-File: LICENSE
Requires-Dist: boto3
Requires-Dist: cantools
Requires-Dist: argcomplete
Dynamic: license-file
